lntopo/__main__.py
lntopo/common.py
lntopo/parser.py
lntopo/timemachine.py
lntopo-0.1.2.dist-info/LICENSE
lntopo-0.1.2.dist-info/METADATA
lntopo-0.1.2.dist-info/WHEEL
lntopo-0.1.2.dist-info/entry_points.txt
lntopo-0.1.2.dist-info/RECORD
