Metadata-Version: 2.1
Name: lntopo
Version: 0.1.2
Summary: 
Author: Christian Decker
Author-email: decker.christian@gmail.com
Requires-Python: >=3.8,<4.0
Classifier: Programming Language :: Python :: 3
Classifier: Programming Language :: Python :: 3.8
Classifier: Programming Language :: Python :: 3.9
Classifier: Programming Language :: Python :: 3.10
Classifier: Programming Language :: Python :: 3.11
Requires-Dist: click (==7.1.2)
Requires-Dist: networkx (>=2.5,<3.0)
Requires-Dist: pydot (>=1.4.2,<2.0.0)
Requires-Dist: pyln-proto (>=0.10,<0.11)
Requires-Dist: tqdm (>=4.50,<5.0)
